dbbs_test_mods/__init__.py
dbbs_test_mods/mod/_glia__dbbs_test_mods__Kca11__0.mod
dbbs_test_mods/mod/_glia__dbbs_test_mods__Kca22__0.mod
dbbs_test_mods/mod/_glia__dbbs_test_mods__Kir23__0.mod
dbbs_test_mods/mod/_glia__dbbs_test_mods__cdp5_CR__0.mod
dbbs_test_mods-0.0.1.data/data/mod/_glia__dbbs_test_mods__Kca11__0.mod
dbbs_test_mods-0.0.1.data/data/mod/_glia__dbbs_test_mods__Kca22__0.mod
dbbs_test_mods-0.0.1.data/data/mod/_glia__dbbs_test_mods__Kir23__0.mod
dbbs_test_mods-0.0.1.data/data/mod/_glia__dbbs_test_mods__cdp5_CR__0.mod
dbbs_test_mods-0.0.1.dist-info/METADATA
dbbs_test_mods-0.0.1.dist-info/WHEEL
dbbs_test_mods-0.0.1.dist-info/entry_points.txt
dbbs_test_mods-0.0.1.dist-info/top_level.txt
dbbs_test_mods-0.0.1.dist-info/RECORD
